waltlabtools/__init__.py
waltlabtools/cal_curve.py
waltlabtools/core.py
waltlabtools/model.py
waltlabtools/mosaic.py
waltlabtools/plot.py
waltlabtools/read.py
waltlabtools-0.5.5.dist-info/LICENSE
waltlabtools-0.5.5.dist-info/METADATA
waltlabtools-0.5.5.dist-info/WHEEL
waltlabtools-0.5.5.dist-info/top_level.txt
waltlabtools-0.5.5.dist-info/RECORD
